{
  "name":"zyugyosyasu",
  "description":"",
  "version":2,
  "minzoom":8,
  "maxzoom":8,
  "center":"138.4593750,34.7916667,8",
  "bounds":"122.9406250,24.0604167,153.9781250,45.5229167",
  "type":"overlay",
  "format":"pbf",
  "json":"{\n  \"vector_layers\":[\n    {\n      \"id\":\"zyugyosyasu\",\n      \"description\":\"\",\n      \"minzoom\":8,\n      \"maxzoom\":8,\n      \"fields\":{\n        \"zyugyosyasu\":\"Number\"\n      }\n    }\n  ],\n  \"tilestats\":{\n    \"layerCount\":1,\n    \"layers\":[\n      {\n        \"layer\":\"zyugyosyasu\",\n        \"count\":329302,\n        \"geometry\":\"Point\",\n        \"attributeCount\":1,\n        \"attributes\":[\n          {\n            \"attribute\":\"zyugyosyasu\",\n            \"count\":1000,\n            \"type\":\"number\",\n            \"values\":[\n              0,\n              1,\n              2,\n              3,\n              4,\n              5,\n              7,\n              8,\n              9,\n              10,\n              11,\n              12,\n              13,\n              14,\n              15,\n              16,\n              17,\n              18,\n              19,\n              20,\n              21,\n              22,\n              23,\n              24,\n              25,\n              26,\n              28,\n              29,\n              30,\n              31,\n              32,\n              35,\n              37,\n              38,\n              39,\n              40,\n              41,\n              44,\n              45,\n              46,\n              49,\n              50,\n              52,\n              55,\n              57,\n              58,\n              59,\n              63,\n              66,\n              68,\n              71,\n              72,\n              73,\n              76,\n              80,\n              81,\n              85,\n              86,\n              88,\n              89,\n              92,\n              93,\n              94,\n              96,\n              97,\n              108,\n              111,\n              120,\n              123,\n              124,\n              133,\n              136,\n              159,\n              186,\n              187,\n              192,\n              219,\n              232,\n              250,\n              256,\n              284,\n              361,\n              377,\n              381,\n              389,\n              398,\n              415,\n              485,\n              496,\n              521,\n              546,\n              555,\n              602,\n              683,\n              754,\n              788,\n              790,\n              1113,\n              2174,\n              2520\n            ],\n            \"min\":0,\n            \"max\":96958\n          }\n        ]\n      }\n    ]\n  }\n}"
}